README.rst
setup.py
do_the_webp/__init__.py
do_the_webp/__main__.py
do_the_webp/compressor.py
do_the_webp/converter.py
do_the_webp/extractor.py
do_the_webp/traverser.py
do_the_webp.egg-info/PKG-INFO
do_the_webp.egg-info/SOURCES.txt
do_the_webp.egg-info/dependency_links.txt
do_the_webp.egg-info/top_level.txt
tests/__init__.py
tests/test_compressor.py
tests/test_converter.py
tests/test_extractor.py
tests/test_traverser.py