Metadata-Version: 1.1
Name: do-the-webp
Version: 0.2.2
Summary: Converts cbz/cbr comic files to webp
Home-page: https://github.com/pedrovanzella/do-the-webp
Author: Pedro Vanzella
Author-email: pedro@pedrovanzella.com
License: UNKNOWN
Platform: UNKNOWN
Classifier: Development Status :: 3 - Alpha
Classifier: Programming Language :: Python
Classifier: Programming Language :: Python :: 3.7
